edc_pharmacy_dashboard/__init__.py
edc_pharmacy_dashboard/apps.py
edc_pharmacy_dashboard/auths.py
edc_pharmacy_dashboard/dashboard_templates.py
edc_pharmacy_dashboard/dashboard_urls.py
edc_pharmacy_dashboard/exceptions.py
edc_pharmacy_dashboard/middleware.py
edc_pharmacy_dashboard/models.py
edc_pharmacy_dashboard/navbars.py
edc_pharmacy_dashboard/patterns.py
edc_pharmacy_dashboard/urls.py
edc_pharmacy_dashboard/migrations/__init__.py
edc_pharmacy_dashboard/model_wrappers/__init__.py
edc_pharmacy_dashboard/model_wrappers/prescription_model_wrapper.py
edc_pharmacy_dashboard/templates/edc_pharmacy_dashboard/appointment_listboard.html
edc_pharmacy_dashboard/templates/edc_pharmacy_dashboard/base_listboard.html
edc_pharmacy_dashboard/templates/edc_pharmacy_dashboard/home.html
edc_pharmacy_dashboard/templates/edc_pharmacy_dashboard/listboard.html
edc_pharmacy_dashboard/templates/edc_pharmacy_dashboard/prescription_listboard.html
edc_pharmacy_dashboard/templates/edc_pharmacy_dashboard/worklist_listboard.html
edc_pharmacy_dashboard/templates/edc_pharmacy_dashboard/listboard/appointment/columns.html
edc_pharmacy_dashboard/templates/edc_pharmacy_dashboard/listboard/appointment/dispensensing_modal.html
edc_pharmacy_dashboard/templates/edc_pharmacy_dashboard/listboard/appointment/results_body.html
edc_pharmacy_dashboard/templates/edc_pharmacy_dashboard/listboard/appointment/results_header.html
edc_pharmacy_dashboard/templates/edc_pharmacy_dashboard/listboard/prescription/columns.html
edc_pharmacy_dashboard/templates/edc_pharmacy_dashboard/listboard/prescription/results_body.html
edc_pharmacy_dashboard/templates/edc_pharmacy_dashboard/listboard/prescription/results_header.html
edc_pharmacy_dashboard/templates/edc_pharmacy_dashboard/listboard/worklist/buttons_column.html
edc_pharmacy_dashboard/templates/edc_pharmacy_dashboard/listboard/worklist/columns.html
edc_pharmacy_dashboard/templates/edc_pharmacy_dashboard/listboard/worklist/results_body.html
edc_pharmacy_dashboard-0.1.9.dist-info/LICENSE
edc_pharmacy_dashboard-0.1.9.dist-info/METADATA
edc_pharmacy_dashboard-0.1.9.dist-info/WHEEL
edc_pharmacy_dashboard-0.1.9.dist-info/top_level.txt
edc_pharmacy_dashboard-0.1.9.dist-info/RECORD
